[
  {
    "topic": "It is a miraculous moment captured by Google Street View.",
    "sources": [
      "reddit"
    ],
    "subreddit": "funny",
    "why": "New post on r/funny \u2022 ~1m ago",
    "exampleUrl": "https://www.reddit.com/r/funny/comments/1s7iriz/it_is_a_miraculous_moment_captured_by_google/"
  },
  {
    "topic": "] REMINDER] ANY political content will earn an immediate 30-day ban\"",
    "sources": [
      "reddit"
    ],
    "subreddit": "funny",
    "why": "New post on r/funny \u2022 ~1m ago",
    "exampleUrl": "https://www.reddit.com/r/funny/comments/160kuuf/reminder_any_political_content_will_earn_an/"
  },
  {
    "topic": "relations",
    "sources": [
      "reddit"
    ],
    "subreddit": "funny",
    "why": "New post on r/funny \u2022 ~1m ago",
    "exampleUrl": "https://www.reddit.com/r/funny/comments/1s7by11/relations/"
  },
  {
    "topic": "Stealing",
    "sources": [
      "reddit"
    ],
    "subreddit": "funny",
    "why": "New post on r/funny \u2022 ~1m ago",
    "exampleUrl": "https://www.reddit.com/r/funny/comments/1s6xy24/stealing/"
  },
  {
    "topic": "[OC] What makes you smile",
    "sources": [
      "reddit"
    ],
    "subreddit": "funny",
    "why": "New post on r/funny \u2022 ~1m ago",
    "exampleUrl": "https://www.reddit.com/r/funny/comments/1s6z4pi/oc_what_makes_you_smile/"
  },
  {
    "topic": "What the hell has youtube become",
    "sources": [
      "reddit"
    ],
    "subreddit": "youtube",
    "why": "New post on r/youtube \u2022 ~1m ago",
    "exampleUrl": "https://www.reddit.com/r/youtube/comments/1s7fwbu/what_the_hell_has_youtube_become/"
  },
  {
    "topic": "Where do you think the line of \"AI-generated content\" lies?",
    "sources": [
      "reddit"
    ],
    "subreddit": "youtube",
    "why": "New post on r/youtube \u2022 ~1m ago",
    "exampleUrl": "https://www.reddit.com/r/youtube/comments/1s6vauy/where_do_you_think_the_line_of_aigenerated/"
  },
  {
    "topic": "Saw this on my IG feed. Why does Druski look like Trisha Paytas lol",
    "sources": [
      "reddit"
    ],
    "subreddit": "youtube",
    "why": "New post on r/youtube \u2022 ~1m ago",
    "exampleUrl": "https://www.reddit.com/r/youtube/comments/1s7doj5/saw_this_on_my_ig_feed_why_does_druski_look_like/"
  },
  {
    "topic": "The Barbie Fest Situation is Insane",
    "sources": [
      "reddit"
    ],
    "subreddit": "youtube",
    "why": "New post on r/youtube \u2022 ~1m ago",
    "exampleUrl": "https://www.reddit.com/r/youtube/comments/1s7hetw/the_barbie_fest_situation_is_insane/"
  },
  {
    "topic": "copyright system is busted.",
    "sources": [
      "reddit"
    ],
    "subreddit": "youtube",
    "why": "New post on r/youtube \u2022 ~1m ago",
    "exampleUrl": "https://www.reddit.com/r/youtube/comments/1s7a63n/copyright_system_is_busted/"
  },
  {
    "topic": "Trump reportedly warns to 'take the oil in Iran' as Tehran targets water, power plants in Kuwait",
    "sources": [
      "reddit"
    ],
    "subreddit": "worldnews",
    "why": "New post on r/worldnews \u2022 ~1m ago",
    "exampleUrl": "https://www.reddit.com/r/worldnews/comments/1s7d530/trump_reportedly_warns_to_take_the_oil_in_iran_as/"
  },
  {
    "topic": "/r/WorldNews Live Thread: Russian Invasion of Ukraine Day 1495, Part 1 (Thread #1642)",
    "sources": [
      "reddit"
    ],
    "subreddit": "worldnews",
    "why": "New post on r/worldnews \u2022 ~1m ago",
    "exampleUrl": "https://www.reddit.com/r/worldnews/comments/1s7g9ns/rworldnews_live_thread_russian_invasion_of/"
  },
  {
    "topic": "/r/WorldNews Discussion Thread: US and Israel launch attack on Iran; Iran retaliates (Thread #11)",
    "sources": [
      "reddit"
    ],
    "subreddit": "worldnews",
    "why": "New post on r/worldnews \u2022 ~1m ago",
    "exampleUrl": "https://www.reddit.com/r/worldnews/comments/1s402bg/rworldnews_discussion_thread_us_and_israel_launch/"
  },
  {
    "topic": "Booby-Trapped Insoles Allegedly Reached Russian Troops",
    "sources": [
      "reddit"
    ],
    "subreddit": "worldnews",
    "why": "New post on r/worldnews \u2022 ~1m ago",
    "exampleUrl": "https://www.reddit.com/r/worldnews/comments/1s7b0z1/boobytrapped_insoles_allegedly_reached_russian/"
  },
  {
    "topic": "Zelenskyy says 10 drone factories have been built worldwide behind Ukraine\u2019s back | Ukrainska Pravda",
    "sources": [
      "reddit"
    ],
    "subreddit": "worldnews",
    "why": "New post on r/worldnews \u2022 ~1m ago",
    "exampleUrl": "https://www.reddit.com/r/worldnews/comments/1s74eze/zelenskyy_says_10_drone_factories_have_been_built/"
  },
  {
    "topic": "Making Friends Monday! Share your game tags here!",
    "sources": [
      "reddit"
    ],
    "subreddit": "gaming",
    "why": "New post on r/gaming \u2022 ~1m ago",
    "exampleUrl": "https://www.reddit.com/r/gaming/comments/1s7idur/making_friends_monday_share_your_game_tags_here/"
  },
  {
    "topic": "PlayStation Console Prices At Launch vs 6 Years Later",
    "sources": [
      "reddit"
    ],
    "subreddit": "gaming",
    "why": "New post on r/gaming \u2022 ~1m ago",
    "exampleUrl": "https://www.reddit.com/r/gaming/comments/1s74jtq/playstation_console_prices_at_launch_vs_6_years/"
  },
  {
    "topic": "Fight the FOMO, ignore PS5 Pro",
    "sources": [
      "reddit"
    ],
    "subreddit": "gaming",
    "why": "New post on r/gaming \u2022 ~1m ago",
    "exampleUrl": "https://www.reddit.com/r/gaming/comments/1s787hc/fight_the_fomo_ignore_ps5_pro/"
  },
  {
    "topic": "Crimson Desert Reaches Peak Steam Concurrent Players At 250K+ And Goes From \"Mixed\" To \"Very Positive\" User Rating, Following Recent Patch",
    "sources": [
      "reddit"
    ],
    "subreddit": "gaming",
    "why": "New post on r/gaming \u2022 ~1m ago",
    "exampleUrl": "https://www.reddit.com/r/gaming/comments/1s6zizd/crimson_desert_reaches_peak_steam_concurrent/"
  },
  {
    "topic": "So i started playing Infinite Warfare today, supposedly one of the best COD campaigns and this is the very first mission. Just wow. Holy shit this game is 10 years old",
    "sources": [
      "reddit"
    ],
    "subreddit": "gaming",
    "why": "New post on r/gaming \u2022 ~1m ago",
    "exampleUrl": "https://www.reddit.com/r/gaming/comments/1s79k7a/so_i_started_playing_infinite_warfare_today/"
  },
  {
    "topic": "Destroying A World That Doesn't Exist",
    "sources": [
      "youtube"
    ],
    "why": "Trending on YouTube \u2022 1,259,409 views \u2022 ~489m old",
    "exampleUrl": "https://www.youtube.com/watch?v=NnTycJg1MIo"
  },
  {
    "topic": "Clips Have Gone To Far",
    "sources": [
      "youtube"
    ],
    "why": "Trending on YouTube \u2022 524,904 views \u2022 ~621m old",
    "exampleUrl": "https://www.youtube.com/watch?v=rvtjABlczGA"
  },
  {
    "topic": "GTA5 - Car Roulette Returns and Wildcat Isn't Straight",
    "sources": [
      "youtube"
    ],
    "why": "Trending on YouTube \u2022 236,098 views \u2022 ~454m old",
    "exampleUrl": "https://www.youtube.com/watch?v=DCaqTgh51OY"
  },
  {
    "topic": "This Game Would Clinch the Playoffs! Wheel of MUT Ep. #54",
    "sources": [
      "youtube"
    ],
    "why": "Trending on YouTube \u2022 191,390 views \u2022 ~609m old",
    "exampleUrl": "https://www.youtube.com/watch?v=wrSR-Cdi3UU"
  },
  {
    "topic": "Cook Out 400",
    "sources": [
      "youtube"
    ],
    "why": "Trending on YouTube \u2022 0 views \u2022 ~131m old",
    "exampleUrl": "https://www.youtube.com/watch?v=eRTxNs0eyHI"
  },
  {
    "topic": "Texas Children's Houston Open, Final Round",
    "sources": [
      "youtube"
    ],
    "why": "Trending on YouTube \u2022 0 views \u2022 ~343m old",
    "exampleUrl": "https://www.youtube.com/watch?v=WW8GCMDbLz4"
  },
  {
    "topic": "The Big Weekend Show",
    "sources": [
      "youtube"
    ],
    "why": "Trending on YouTube \u2022 0 views \u2022 ~84m old",
    "exampleUrl": "https://www.youtube.com/watch?v=XlZ4dT3Vg9s"
  },
  {
    "topic": "Texas Rangers at Philadelphia Phillies",
    "sources": [
      "youtube"
    ],
    "why": "Trending on YouTube \u2022 0 views \u2022 ~70m old",
    "exampleUrl": "https://www.youtube.com/watch?v=x57gWZCSlAM"
  },
  {
    "topic": "LIQUI MOLY Pro Watercross National Tour: Orange",
    "sources": [
      "youtube"
    ],
    "why": "Trending on YouTube \u2022 0 views \u2022 ~134m old",
    "exampleUrl": "https://www.youtube.com/watch?v=Y3Rry_mXmeg"
  },
  {
    "topic": "The Patriot",
    "sources": [
      "youtube"
    ],
    "why": "Trending on YouTube \u2022 0 views \u2022 ~107m old",
    "exampleUrl": "https://www.youtube.com/watch?v=i8Ok3-W35LU"
  },
  {
    "topic": "College GameDay",
    "sources": [
      "youtube"
    ],
    "why": "Trending on YouTube \u2022 0 views \u2022 ~549m old",
    "exampleUrl": "https://www.youtube.com/watch?v=Bpu4Sc05Yvc"
  },
  {
    "topic": "Tennessee at Vanderbilt",
    "sources": [
      "youtube"
    ],
    "why": "Trending on YouTube \u2022 0 views \u2022 ~362m old",
    "exampleUrl": "https://www.youtube.com/watch?v=rtRAIhyZ76g"
  },
  {
    "topic": "Goodfellas",
    "sources": [
      "youtube"
    ],
    "why": "Trending on YouTube \u2022 0 views \u2022 ~290m old",
    "exampleUrl": "https://www.youtube.com/watch?v=FScV76cEyaU"
  },
  {
    "topic": "CNN Newsroom",
    "sources": [
      "youtube"
    ],
    "why": "Trending on YouTube \u2022 0 views \u2022 ~208m old",
    "exampleUrl": "https://www.youtube.com/watch?v=OjeAeoNhiOE"
  }
]