[
  {
    "topic": "] REMINDER] ANY political content will earn an immediate 30-day ban\"",
    "sources": [
      "reddit"
    ],
    "subreddit": "funny",
    "why": "New post on r/funny \u2022 ~1m ago",
    "exampleUrl": "https://www.reddit.com/r/funny/comments/160kuuf/reminder_any_political_content_will_earn_an/"
  },
  {
    "topic": "My Sleep Paralysis Demon and I go way back",
    "sources": [
      "reddit"
    ],
    "subreddit": "funny",
    "why": "New post on r/funny \u2022 ~1m ago",
    "exampleUrl": "https://www.reddit.com/r/funny/comments/1qnp2pk/my_sleep_paralysis_demon_and_i_go_way_back/"
  },
  {
    "topic": "The bait was convincing",
    "sources": [
      "reddit"
    ],
    "subreddit": "funny",
    "why": "New post on r/funny \u2022 ~1m ago",
    "exampleUrl": "https://www.reddit.com/r/funny/comments/1qncorb/the_bait_was_convincing/"
  },
  {
    "topic": "affection",
    "sources": [
      "reddit"
    ],
    "subreddit": "funny",
    "why": "New post on r/funny \u2022 ~1m ago",
    "exampleUrl": "https://www.reddit.com/r/funny/comments/1qn5r95/affection/"
  },
  {
    "topic": "Tip to have a sexy waistline",
    "sources": [
      "reddit"
    ],
    "subreddit": "funny",
    "why": "New post on r/funny \u2022 ~1m ago",
    "exampleUrl": "https://www.reddit.com/r/funny/comments/1qn9ryz/tip_to_have_a_sexy_waistline/"
  },
  {
    "topic": "Has anyone else noticed this trend of \u201cremember this old controversial creator? Their life is ruined now\u201d videos?",
    "sources": [
      "reddit"
    ],
    "subreddit": "youtube",
    "why": "New post on r/youtube \u2022 ~1m ago",
    "exampleUrl": "https://www.reddit.com/r/youtube/comments/1qn6yrb/has_anyone_else_noticed_this_trend_of_remember/"
  },
  {
    "topic": "Why aren't there as many big YouTubers making entertaining \"fun\" videos anymore?",
    "sources": [
      "reddit"
    ],
    "subreddit": "youtube",
    "why": "New post on r/youtube \u2022 ~1m ago",
    "exampleUrl": "https://www.reddit.com/r/youtube/comments/1qmzj6b/why_arent_there_as_many_big_youtubers_making/"
  },
  {
    "topic": "YouTube is demonetizing AI channels. How do you see this changing the platform?",
    "sources": [
      "reddit"
    ],
    "subreddit": "youtube",
    "why": "New post on r/youtube \u2022 ~1m ago",
    "exampleUrl": "https://www.reddit.com/r/youtube/comments/1qnjpfg/youtube_is_demonetizing_ai_channels_how_do_you/"
  },
  {
    "topic": "All official youtube rewind videos are now private, in other words: gone.",
    "sources": [
      "reddit"
    ],
    "subreddit": "youtube",
    "why": "New post on r/youtube \u2022 ~1m ago",
    "exampleUrl": "https://www.reddit.com/r/youtube/comments/1qn2mtl/all_official_youtube_rewind_videos_are_now/"
  },
  {
    "topic": "Another day, another ad block war happening behind the curtain.",
    "sources": [
      "reddit"
    ],
    "subreddit": "youtube",
    "why": "New post on r/youtube \u2022 ~1m ago",
    "exampleUrl": "https://www.reddit.com/r/youtube/comments/1qnfj4k/another_day_another_ad_block_war_happening_behind/"
  },
  {
    "topic": "Sepp Blatter suggests fans should not travel to US for World Cup",
    "sources": [
      "reddit"
    ],
    "subreddit": "worldnews",
    "why": "New post on r/worldnews \u2022 ~1m ago",
    "exampleUrl": "https://www.reddit.com/r/worldnews/comments/1qnnnt6/sepp_blatter_suggests_fans_should_not_travel_to/"
  },
  {
    "topic": "/r/WorldNews Live Thread: Russian Invasion of Ukraine Day 1432, Part 1 (Thread #1579)",
    "sources": [
      "reddit"
    ],
    "subreddit": "worldnews",
    "why": "New post on r/worldnews \u2022 ~1m ago",
    "exampleUrl": "https://www.reddit.com/r/worldnews/comments/1qnfvf2/rworldnews_live_thread_russian_invasion_of/"
  },
  {
    "topic": "European Commission to open investigation into Elon Musk\u2019s X",
    "sources": [
      "reddit"
    ],
    "subreddit": "worldnews",
    "why": "New post on r/worldnews \u2022 ~1m ago",
    "exampleUrl": "https://www.reddit.com/r/worldnews/comments/1qncrcu/european_commission_to_open_investigation_into/"
  },
  {
    "topic": "Volkswagen considers pulling out of US factory plans over tariffs",
    "sources": [
      "reddit"
    ],
    "subreddit": "worldnews",
    "why": "New post on r/worldnews \u2022 ~1m ago",
    "exampleUrl": "https://www.reddit.com/r/worldnews/comments/1qnozxa/volkswagen_considers_pulling_out_of_us_factory/"
  },
  {
    "topic": "Israel recovers body of last hostage in Gaza",
    "sources": [
      "reddit"
    ],
    "subreddit": "worldnews",
    "why": "New post on r/worldnews \u2022 ~1m ago",
    "exampleUrl": "https://www.reddit.com/r/worldnews/comments/1qnh0ru/israel_recovers_body_of_last_hostage_in_gaza/"
  },
  {
    "topic": "Pedro Pascal speaks out against ICE again",
    "sources": [
      "reddit"
    ],
    "subreddit": "popculturechat",
    "why": "New post on r/popculturechat \u2022 ~1m ago",
    "exampleUrl": "https://www.reddit.com/r/popculturechat/comments/1qnjljw/pedro_pascal_speaks_out_against_ice_again/"
  },
  {
    "topic": "Will you be playing Highguard?",
    "sources": [
      "reddit"
    ],
    "subreddit": "gaming",
    "why": "New post on r/gaming \u2022 ~1m ago",
    "exampleUrl": "https://www.reddit.com/r/gaming/comments/1qno30h/will_you_be_playing_highguard/"
  },
  {
    "topic": "Making Friends Monday! Share your game tags here!",
    "sources": [
      "reddit"
    ],
    "subreddit": "gaming",
    "why": "New post on r/gaming \u2022 ~1m ago",
    "exampleUrl": "https://www.reddit.com/r/gaming/comments/1qn8zif/making_friends_monday_share_your_game_tags_here/"
  },
  {
    "topic": "The Sims 4's most notorious sex mod gets launched 400,000 times a day, which is more people than I realized were even playing The Sims every day",
    "sources": [
      "reddit"
    ],
    "subreddit": "gaming",
    "why": "New post on r/gaming \u2022 ~1m ago",
    "exampleUrl": "https://www.reddit.com/r/gaming/comments/1qnm0fi/the_sims_4s_most_notorious_sex_mod_gets_launched/"
  },
  {
    "topic": "\u2018Highguard\u2019: Wildlight Founders on How Their Debut Game Is Not Like \u2018Concord\u2019 or \u2018Overwatch\u2019: \"Our trailer didn\u2019t highlight that well, and we\u2019ll own that. But at the end of the day, we\u2019re really excited just to get the game out on Monday and let it speak for itself\"",
    "sources": [
      "reddit"
    ],
    "subreddit": "gaming",
    "why": "New post on r/gaming \u2022 ~1m ago",
    "exampleUrl": "https://www.reddit.com/r/gaming/comments/1qnnv5v/highguard_wildlight_founders_on_how_their_debut/"
  },
  {
    "topic": "KiiiKiii \ud0a4\ud0a4 '404 (New Era)' MV",
    "sources": [
      "youtube"
    ],
    "why": "Trending on YouTube \u2022 1,115,471 views \u2022 ~643m old",
    "exampleUrl": "https://www.youtube.com/watch?v=zhHB4dZTChw"
  },
  {
    "topic": "\u3010Ado\u3011\u30a8\u30f3\u30bc\u30eb\u30b7\u30fc\u30af\uff08Official Audio\uff09",
    "sources": [
      "youtube"
    ],
    "why": "Trending on YouTube \u2022 145,571 views \u2022 ~401m old",
    "exampleUrl": "https://www.youtube.com/watch?v=ukdidk1CkaQ"
  },
  {
    "topic": "\u7a32\u8449\u66c7\u300e\u30b9\u30dd\u30c3\u30c8\u30ec\u30a4\u30c8\u300fVo. \u6b4c\u611b\u30e6\u30ad",
    "sources": [
      "youtube"
    ],
    "why": "Trending on YouTube \u2022 179,197 views \u2022 ~583m old",
    "exampleUrl": "https://www.youtube.com/watch?v=STBoCK69vVQ"
  },
  {
    "topic": "WWE 2K26 TEASER BREAKDOWN! HUGE DETAILS REVEALED!",
    "sources": [
      "youtube"
    ],
    "why": "Trending on YouTube \u2022 8,592 views \u2022 ~192m old",
    "exampleUrl": "https://www.youtube.com/watch?v=nh2v-eiLVZs"
  },
  {
    "topic": "See Rapper Travis Scott in New \u2018Odyssey\u2019 Trailer",
    "sources": [
      "youtube"
    ],
    "why": "Trending on YouTube \u2022 9,536 views \u2022 ~283m old",
    "exampleUrl": "https://www.youtube.com/watch?v=xFoOGGQCT4A"
  },
  {
    "topic": "Star Wars: Return of the Jedi",
    "sources": [
      "youtube"
    ],
    "why": "Trending on YouTube \u2022 0 views \u2022 ~382m old",
    "exampleUrl": "https://www.youtube.com/watch?v=JftMT_V67X0"
  }
]