[
  {
    "topic": "] REMINDER] ANY political content will earn an immediate 30-day ban\"",
    "sources": [
      "reddit"
    ],
    "subreddit": "funny",
    "why": "New post on r/funny \u2022 ~1m ago",
    "exampleUrl": "https://www.reddit.com/r/funny/comments/160kuuf/reminder_any_political_content_will_earn_an/"
  },
  {
    "topic": "No, no, I don't need this service. Do you not hear me? Where's the manager?",
    "sources": [
      "reddit"
    ],
    "subreddit": "funny",
    "why": "New post on r/funny \u2022 ~1m ago",
    "exampleUrl": "https://www.reddit.com/r/funny/comments/1tguoch/no_no_i_dont_need_this_service_do_you_not_hear_me/"
  },
  {
    "topic": "That\u2019s One Way to Keep My Kids Away From My Tea",
    "sources": [
      "reddit"
    ],
    "subreddit": "funny",
    "why": "New post on r/funny \u2022 ~1m ago",
    "exampleUrl": "https://www.reddit.com/r/funny/comments/1thaby2/thats_one_way_to_keep_my_kids_away_from_my_tea/"
  },
  {
    "topic": "My dad met my bird",
    "sources": [
      "reddit"
    ],
    "subreddit": "funny",
    "why": "New post on r/funny \u2022 ~1m ago",
    "exampleUrl": "https://www.reddit.com/r/funny/comments/1tgzhy5/my_dad_met_my_bird/"
  },
  {
    "topic": "\"Damn what are they cooking? \"",
    "sources": [
      "reddit"
    ],
    "subreddit": "funny",
    "why": "New post on r/funny \u2022 ~1m ago",
    "exampleUrl": "https://www.reddit.com/r/funny/comments/1thhlz2/damn_what_are_they_cooking/"
  },
  {
    "topic": "What is this point of these live streams? Why are there so many of them in this exact style? Thanks. Some are just the same people with a bunch of accounts with the same livestream, I don't understand.",
    "sources": [
      "reddit"
    ],
    "subreddit": "youtube",
    "why": "New post on r/youtube \u2022 ~1m ago",
    "exampleUrl": "https://www.reddit.com/r/youtube/comments/1th6bm1/what_is_this_point_of_these_live_streams_why_are/"
  },
  {
    "topic": "it is the truth though",
    "sources": [
      "reddit"
    ],
    "subreddit": "youtube",
    "why": "New post on r/youtube \u2022 ~1m ago",
    "exampleUrl": "https://www.reddit.com/r/youtube/comments/1tgp7aa/it_is_the_truth_though/"
  },
  {
    "topic": "Youtube Automatically Subscribed Me to TPUSA",
    "sources": [
      "reddit"
    ],
    "subreddit": "youtube",
    "why": "New post on r/youtube \u2022 ~1m ago",
    "exampleUrl": "https://www.reddit.com/r/youtube/comments/1thawjq/youtube_automatically_subscribed_me_to_tpusa/"
  },
  {
    "topic": "What's going on",
    "sources": [
      "reddit"
    ],
    "subreddit": "youtube",
    "why": "New post on r/youtube \u2022 ~1m ago",
    "exampleUrl": "https://www.reddit.com/r/youtube/comments/1thd0t2/whats_going_on/"
  },
  {
    "topic": "Frustrating garbage now.",
    "sources": [
      "reddit"
    ],
    "subreddit": "youtube",
    "why": "New post on r/youtube \u2022 ~1m ago",
    "exampleUrl": "https://www.reddit.com/r/youtube/comments/1th8hq1/frustrating_garbage_now/"
  },
  {
    "topic": "/r/WorldNews Live Thread: Russian Invasion of Ukraine Day 1545, Part 1 (Thread #1692)",
    "sources": [
      "reddit"
    ],
    "subreddit": "worldnews",
    "why": "New post on r/worldnews \u2022 ~1m ago",
    "exampleUrl": "https://www.reddit.com/r/worldnews/comments/1thbixw/rworldnews_live_thread_russian_invasion_of/"
  },
  {
    "topic": "/r/WorldNews Discussion Thread: US and Israel launch attack on Iran; Iran retaliates (Thread #17)",
    "sources": [
      "reddit"
    ],
    "subreddit": "worldnews",
    "why": "New post on r/worldnews \u2022 ~1m ago",
    "exampleUrl": "https://www.reddit.com/r/worldnews/comments/1t1399d/rworldnews_discussion_thread_us_and_israel_launch/"
  },
  {
    "topic": "Xi Jinping Told Donald Trump That Vladimir Putin Might Regret The Ukraine Invasion: Report",
    "sources": [
      "reddit"
    ],
    "subreddit": "worldnews",
    "why": "New post on r/worldnews \u2022 ~1m ago",
    "exampleUrl": "https://www.reddit.com/r/worldnews/comments/1thflaj/xi_jinping_told_donald_trump_that_vladimir_putin/"
  },
  {
    "topic": "Trump says he's postponing 'scheduled attack of Iran tomorrow' at Middle East leaders' request",
    "sources": [
      "reddit"
    ],
    "subreddit": "worldnews",
    "why": "New post on r/worldnews \u2022 ~1m ago",
    "exampleUrl": "https://www.reddit.com/r/worldnews/comments/1tgxnx9/trump_says_hes_postponing_scheduled_attack_of/"
  },
  {
    "topic": "Marcos says Philippines would be involved in any Taiwan conflict",
    "sources": [
      "reddit"
    ],
    "subreddit": "worldnews",
    "why": "New post on r/worldnews \u2022 ~1m ago",
    "exampleUrl": "https://www.reddit.com/r/worldnews/comments/1thbrpz/marcos_says_philippines_would_be_involved_in_any/"
  },
  {
    "topic": "Making Friends Monday! Share your game tags here!",
    "sources": [
      "reddit"
    ],
    "subreddit": "gaming",
    "why": "New post on r/gaming \u2022 ~1m ago",
    "exampleUrl": "https://www.reddit.com/r/gaming/comments/1tgdn84/making_friends_monday_share_your_game_tags_here/"
  },
  {
    "topic": "It's official: Steam decrees 'bullet heaven' the name of the Vampire Survivors genre",
    "sources": [
      "reddit"
    ],
    "subreddit": "gaming",
    "why": "New post on r/gaming \u2022 ~1m ago",
    "exampleUrl": "https://www.reddit.com/r/gaming/comments/1th4rw1/its_official_steam_decrees_bullet_heaven_the_name/"
  },
  {
    "topic": "Don't expect to kill fish in a future Subnautica 2 patch: 'You are here to exist on this planet, not to dominate it'",
    "sources": [
      "reddit"
    ],
    "subreddit": "gaming",
    "why": "New post on r/gaming \u2022 ~1m ago",
    "exampleUrl": "https://www.reddit.com/r/gaming/comments/1thbe57/dont_expect_to_kill_fish_in_a_future_subnautica_2/"
  },
  {
    "topic": "Its Official: PlayStation Boss Hermen Hulst told staff in a town hall Monday morning that the company's narrative single-player games will now be PlayStation exclusive",
    "sources": [
      "reddit"
    ],
    "subreddit": "gaming",
    "why": "New post on r/gaming \u2022 ~1m ago",
    "exampleUrl": "https://www.reddit.com/r/gaming/comments/1tgy89i/its_official_playstation_boss_hermen_hulst_told/"
  },
  {
    "topic": "Helping my dad clean out a spare room and found a bunch of our old games.",
    "sources": [
      "reddit"
    ],
    "subreddit": "gaming",
    "why": "New post on r/gaming \u2022 ~1m ago",
    "exampleUrl": "https://www.reddit.com/r/gaming/comments/1tgqo7d/helping_my_dad_clean_out_a_spare_room_and_found_a/"
  },
  {
    "topic": "Character Trailer - \"Nicole: An Epic Adventure Story\" | Genshin Impact #GenshinImpact #Nicole",
    "sources": [
      "youtube"
    ],
    "why": "Trending on YouTube \u2022 140,875 views \u2022 ~362m old",
    "exampleUrl": "https://www.youtube.com/watch?v=xDdrmoSh3W4"
  },
  {
    "topic": "Jesse Watters Primetime",
    "sources": [
      "youtube"
    ],
    "why": "Trending on YouTube \u2022 0 views \u2022 ~160m old",
    "exampleUrl": "https://www.youtube.com/watch?v=_BxFH1cVInA"
  },
  {
    "topic": "The Rachel Maddow Show",
    "sources": [
      "youtube"
    ],
    "why": "Trending on YouTube \u2022 0 views \u2022 ~104m old",
    "exampleUrl": "https://www.youtube.com/watch?v=e7leAtwjZBI"
  },
  {
    "topic": "The Garden Party",
    "sources": [
      "youtube"
    ],
    "why": "Trending on YouTube \u2022 0 views \u2022 ~145m old",
    "exampleUrl": "https://www.youtube.com/watch?v=LpOrutDy7Hs"
  },
  {
    "topic": "Anderson Cooper 360",
    "sources": [
      "youtube"
    ],
    "why": "Trending on YouTube \u2022 0 views \u2022 ~195m old",
    "exampleUrl": "https://www.youtube.com/watch?v=_hTASyMB7p4"
  },
  {
    "topic": "The Point",
    "sources": [
      "youtube"
    ],
    "why": "Trending on YouTube \u2022 0 views \u2022 ~227m old",
    "exampleUrl": "https://www.youtube.com/watch?v=GRscWiVvUJY"
  },
  {
    "topic": "The Bourne Identity",
    "sources": [
      "youtube"
    ],
    "why": "Trending on YouTube \u2022 0 views \u2022 ~144m old",
    "exampleUrl": "https://www.youtube.com/watch?v=I8XedS3ioM0"
  }
]