[
  {
    "topic": "] REMINDER] ANY political content will earn an immediate 30-day ban\"",
    "sources": [
      "reddit"
    ],
    "subreddit": "funny",
    "why": "New post on r/funny \u2022 ~1m ago",
    "exampleUrl": "https://www.reddit.com/r/funny/comments/160kuuf/reminder_any_political_content_will_earn_an/"
  },
  {
    "topic": "3/10 Dismount \ud83d\ude05",
    "sources": [
      "reddit"
    ],
    "subreddit": "funny",
    "why": "New post on r/funny \u2022 ~1m ago",
    "exampleUrl": "https://www.reddit.com/r/funny/comments/1qif1q4/310_dismount/"
  },
  {
    "topic": "You steal it, you wear it.",
    "sources": [
      "reddit"
    ],
    "subreddit": "funny",
    "why": "New post on r/funny \u2022 ~1m ago",
    "exampleUrl": "https://www.reddit.com/r/funny/comments/1qi743l/you_steal_it_you_wear_it/"
  },
  {
    "topic": "Too broke for water \ud83d\ude2d",
    "sources": [
      "reddit"
    ],
    "subreddit": "funny",
    "why": "New post on r/funny \u2022 ~1m ago",
    "exampleUrl": "https://www.reddit.com/r/funny/comments/1qii6wo/too_broke_for_water/"
  },
  {
    "topic": "Pretending to be a car",
    "sources": [
      "reddit"
    ],
    "subreddit": "funny",
    "why": "New post on r/funny \u2022 ~1m ago",
    "exampleUrl": "https://www.reddit.com/r/funny/comments/1qimv1h/pretending_to_be_a_car/"
  },
  {
    "topic": "Why is this even allowed?",
    "sources": [
      "reddit"
    ],
    "subreddit": "youtube",
    "why": "New post on r/youtube \u2022 ~1m ago",
    "exampleUrl": "https://www.reddit.com/r/youtube/comments/1qhwe2j/why_is_this_even_allowed/"
  },
  {
    "topic": "i\u2019m going to lose my mind with these ads.",
    "sources": [
      "reddit"
    ],
    "subreddit": "youtube",
    "why": "New post on r/youtube \u2022 ~1m ago",
    "exampleUrl": "https://www.reddit.com/r/youtube/comments/1qii8v9/im_going_to_lose_my_mind_with_these_ads/"
  },
  {
    "topic": "Doritos are apparently a chocolate brand according to youtube",
    "sources": [
      "reddit"
    ],
    "subreddit": "youtube",
    "why": "New post on r/youtube \u2022 ~1m ago",
    "exampleUrl": "https://www.reddit.com/r/youtube/comments/1qij4ft/doritos_are_apparently_a_chocolate_brand/"
  },
  {
    "topic": "What Youtuber is this for you?",
    "sources": [
      "reddit"
    ],
    "subreddit": "youtube",
    "why": "New post on r/youtube \u2022 ~1m ago",
    "exampleUrl": "https://www.reddit.com/r/youtube/comments/1qi3yds/what_youtuber_is_this_for_you/"
  },
  {
    "topic": "Every year, every month.",
    "sources": [
      "reddit"
    ],
    "subreddit": "youtube",
    "why": "New post on r/youtube \u2022 ~1m ago",
    "exampleUrl": "https://www.reddit.com/r/youtube/comments/1qhxmns/every_year_every_month/"
  },
  {
    "topic": "Macron on Trump leaking their private messages: \"I stand by my words\"",
    "sources": [
      "reddit"
    ],
    "subreddit": "worldnews",
    "why": "New post on r/worldnews \u2022 ~1m ago",
    "exampleUrl": "https://www.reddit.com/r/worldnews/comments/1qifvu2/macron_on_trump_leaking_their_private_messages_i/"
  },
  {
    "topic": "/r/WorldNews Live Thread: Russian Invasion of Ukraine Day 1427, Part 1 (Thread #1574)",
    "sources": [
      "reddit"
    ],
    "subreddit": "worldnews",
    "why": "New post on r/worldnews \u2022 ~1m ago",
    "exampleUrl": "https://www.reddit.com/r/worldnews/comments/1qinlns/rworldnews_live_thread_russian_invasion_of/"
  },
  {
    "topic": "Canada is positioning itself on Greenland knowing it could be next",
    "sources": [
      "reddit"
    ],
    "subreddit": "worldnews",
    "why": "New post on r/worldnews \u2022 ~1m ago",
    "exampleUrl": "https://www.reddit.com/r/worldnews/comments/1qikg7p/canada_is_positioning_itself_on_greenland_knowing/"
  },
  {
    "topic": "Danish pension fund to sell $100 million in U.S. Treasuries due to \"poor U.S. government finances\"",
    "sources": [
      "reddit"
    ],
    "subreddit": "worldnews",
    "why": "New post on r/worldnews \u2022 ~1m ago",
    "exampleUrl": "https://www.reddit.com/r/worldnews/comments/1qifazb/danish_pension_fund_to_sell_100_million_in_us/"
  },
  {
    "topic": "Danish pension fund to sell $100 million in Treasuries, citing 'poor' U.S. government finances",
    "sources": [
      "reddit"
    ],
    "subreddit": "worldnews",
    "why": "New post on r/worldnews \u2022 ~1m ago",
    "exampleUrl": "https://www.reddit.com/r/worldnews/comments/1qi7tdk/danish_pension_fund_to_sell_100_million_in/"
  },
  {
    "topic": "Making Friends Monday! Share your game tags here!",
    "sources": [
      "reddit"
    ],
    "subreddit": "gaming",
    "why": "New post on r/gaming \u2022 ~1m ago",
    "exampleUrl": "https://www.reddit.com/r/gaming/comments/1qgx8q5/making_friends_monday_share_your_game_tags_here/"
  },
  {
    "topic": "I miss when PC games came in a big box",
    "sources": [
      "reddit"
    ],
    "subreddit": "gaming",
    "why": "New post on r/gaming \u2022 ~1m ago",
    "exampleUrl": "https://www.reddit.com/r/gaming/comments/1qile2s/i_miss_when_pc_games_came_in_a_big_box/"
  },
  {
    "topic": "Highguard Is One Week Away, And The Only Person Who's Advertised It Is Geoff Keighley",
    "sources": [
      "reddit"
    ],
    "subreddit": "gaming",
    "why": "New post on r/gaming \u2022 ~1m ago",
    "exampleUrl": "https://www.reddit.com/r/gaming/comments/1qi3kow/highguard_is_one_week_away_and_the_only_person/"
  },
  {
    "topic": "Still 1 of my favorite classic examples between Japanese and American cover arts...",
    "sources": [
      "reddit"
    ],
    "subreddit": "gaming",
    "why": "New post on r/gaming \u2022 ~1m ago",
    "exampleUrl": "https://www.reddit.com/r/gaming/comments/1qi9oiv/still_1_of_my_favorite_classic_examples_between/"
  },
  {
    "topic": "Show me the Champion of Light \ud83c\udfb6 (Alan Wake 2, 2023)",
    "sources": [
      "reddit"
    ],
    "subreddit": "gaming",
    "why": "New post on r/gaming \u2022 ~1m ago",
    "exampleUrl": "https://www.reddit.com/r/gaming/comments/1qie1gh/show_me_the_champion_of_light_alan_wake_2_2023/"
  },
  {
    "topic": "I Got the new TACO BASE in Steal A Brainrot..",
    "sources": [
      "youtube"
    ],
    "why": "Trending on YouTube \u2022 952,363 views \u2022 ~290m old",
    "exampleUrl": "https://www.youtube.com/watch?v=ciURKxo-zsU"
  },
  {
    "topic": "I Got Trained By the World's Best Minecraft Player",
    "sources": [
      "youtube"
    ],
    "why": "Trending on YouTube \u2022 454,875 views \u2022 ~367m old",
    "exampleUrl": "https://www.youtube.com/watch?v=D7hmj_cT-Qk"
  },
  {
    "topic": "We Played The Most Hilarious Game of 2026",
    "sources": [
      "youtube"
    ],
    "why": "Trending on YouTube \u2022 223,153 views \u2022 ~298m old",
    "exampleUrl": "https://www.youtube.com/watch?v=AUWH7uHPgOY"
  },
  {
    "topic": "Finishing The 67 Troll Tower In Roblox!",
    "sources": [
      "youtube"
    ],
    "why": "Trending on YouTube \u2022 200,760 views \u2022 ~550m old",
    "exampleUrl": "https://www.youtube.com/watch?v=XK6mHWUAC9I"
  },
  {
    "topic": "Honest Trailers | The Lord of the Rings: The Two Towers",
    "sources": [
      "youtube"
    ],
    "why": "Trending on YouTube \u2022 209,144 views \u2022 ~650m old",
    "exampleUrl": "https://www.youtube.com/watch?v=h5CtjDLvUVk"
  },
  {
    "topic": "Sonic Presents: The Chaotix Casefiles Trailer",
    "sources": [
      "youtube"
    ],
    "why": "Trending on YouTube \u2022 222,566 views \u2022 ~706m old",
    "exampleUrl": "https://www.youtube.com/watch?v=BftIr01R0uU"
  },
  {
    "topic": "Something Feels Electric About This Slot",
    "sources": [
      "youtube"
    ],
    "why": "Trending on YouTube \u2022 156,591 views \u2022 ~546m old",
    "exampleUrl": "https://www.youtube.com/watch?v=uVsNH8tgVQs"
  },
  {
    "topic": "OK, Let\u2019s Talk About the Avengers Doomsday TIMESTAMPS\u2026",
    "sources": [
      "youtube"
    ],
    "why": "Trending on YouTube \u2022 76,690 views \u2022 ~426m old",
    "exampleUrl": "https://www.youtube.com/watch?v=U4u0cdUgV5Q"
  },
  {
    "topic": "Imposter",
    "sources": [
      "youtube"
    ],
    "why": "Trending on YouTube \u2022 76,698 views \u2022 ~618m old",
    "exampleUrl": "https://www.youtube.com/watch?v=0aOU-LBtxUI"
  },
  {
    "topic": "For Honor - Official Juren Hero Reveal Trailer",
    "sources": [
      "youtube"
    ],
    "why": "Trending on YouTube \u2022 84,750 views \u2022 ~711m old",
    "exampleUrl": "https://www.youtube.com/watch?v=6iX0aiIcYls"
  },
  {
    "topic": "Midnight Pre-Expansion Update Trailer | World of Warcraft",
    "sources": [
      "youtube"
    ],
    "why": "Trending on YouTube \u2022 62,833 views \u2022 ~648m old",
    "exampleUrl": "https://www.youtube.com/watch?v=0yqrgPk56Ns"
  },
  {
    "topic": "Josiah Queen - demons (Official Music Video)",
    "sources": [
      "youtube"
    ],
    "why": "Trending on YouTube \u2022 39,187 views \u2022 ~711m old",
    "exampleUrl": "https://www.youtube.com/watch?v=xwXP0pXGQyU"
  },
  {
    "topic": "FattMack - White Knight [Official Music Video]",
    "sources": [
      "youtube"
    ],
    "why": "Trending on YouTube \u2022 16,271 views \u2022 ~471m old",
    "exampleUrl": "https://www.youtube.com/watch?v=o0Q9D2Tn_NY"
  },
  {
    "topic": "Topoppgen - twin towers (Official Video)",
    "sources": [
      "youtube"
    ],
    "why": "Trending on YouTube \u2022 17,581 views \u2022 ~530m old",
    "exampleUrl": "https://www.youtube.com/watch?v=v1E2jOkTtng"
  }
]