[
  {
    "topic": "Throbbin from Gyattham",
    "sources": [
      "reddit"
    ],
    "subreddit": "funny",
    "why": "New post on r/funny \u2022 ~1m ago",
    "exampleUrl": "https://www.reddit.com/r/funny/comments/1rdns44/throbbin_from_gyattham/"
  },
  {
    "topic": "] REMINDER] ANY political content will earn an immediate 30-day ban\"",
    "sources": [
      "reddit"
    ],
    "subreddit": "funny",
    "why": "New post on r/funny \u2022 ~1m ago",
    "exampleUrl": "https://www.reddit.com/r/funny/comments/160kuuf/reminder_any_political_content_will_earn_an/"
  },
  {
    "topic": "It IS big",
    "sources": [
      "reddit"
    ],
    "subreddit": "funny",
    "why": "New post on r/funny \u2022 ~1m ago",
    "exampleUrl": "https://www.reddit.com/r/funny/comments/1rdewzv/it_is_big/"
  },
  {
    "topic": "Every outdoor runner",
    "sources": [
      "reddit"
    ],
    "subreddit": "funny",
    "why": "New post on r/funny \u2022 ~1m ago",
    "exampleUrl": "https://www.reddit.com/r/funny/comments/1rdjdxt/every_outdoor_runner/"
  },
  {
    "topic": "Fast doggo",
    "sources": [
      "reddit"
    ],
    "subreddit": "funny",
    "why": "New post on r/funny \u2022 ~1m ago",
    "exampleUrl": "https://www.reddit.com/r/funny/comments/1rdckal/fast_doggo/"
  },
  {
    "topic": "I cannot unsee it now tf",
    "sources": [
      "reddit"
    ],
    "subreddit": "youtube",
    "why": "New post on r/youtube \u2022 ~1m ago",
    "exampleUrl": "https://www.reddit.com/r/youtube/comments/1rd8cgy/i_cannot_unsee_it_now_tf/"
  },
  {
    "topic": "Who else agrees that Mr.beast kinda ruined YouTube a bit",
    "sources": [
      "reddit"
    ],
    "subreddit": "youtube",
    "why": "New post on r/youtube \u2022 ~1m ago",
    "exampleUrl": "https://www.reddit.com/r/youtube/comments/1rckdu7/who_else_agrees_that_mrbeast_kinda_ruined_youtube/"
  },
  {
    "topic": "Wtf is this?",
    "sources": [
      "reddit"
    ],
    "subreddit": "youtube",
    "why": "New post on r/youtube \u2022 ~1m ago",
    "exampleUrl": "https://www.reddit.com/r/youtube/comments/1rd86dj/wtf_is_this/"
  },
  {
    "topic": "Who exactly is the target audience ? Adults ? I think not",
    "sources": [
      "reddit"
    ],
    "subreddit": "youtube",
    "why": "New post on r/youtube \u2022 ~1m ago",
    "exampleUrl": "https://www.reddit.com/r/youtube/comments/1rdikuq/who_exactly_is_the_target_audience_adults_i_think/"
  },
  {
    "topic": "I was just scrolling through my fyp until this shit randomly pop up \ud83d\ude2d",
    "sources": [
      "reddit"
    ],
    "subreddit": "youtube",
    "why": "New post on r/youtube \u2022 ~1m ago",
    "exampleUrl": "https://www.reddit.com/r/youtube/comments/1rd9tco/i_was_just_scrolling_through_my_fyp_until_this/"
  },
  {
    "topic": "Mexico weighs legal action after Musk links president to drug cartels",
    "sources": [
      "reddit"
    ],
    "subreddit": "worldnews",
    "why": "New post on r/worldnews \u2022 ~1m ago",
    "exampleUrl": "https://www.reddit.com/r/worldnews/comments/1rdl280/mexico_weighs_legal_action_after_musk_links/"
  },
  {
    "topic": "/r/WorldNews Live Thread: Russian Invasion of Ukraine Day 1461, Part 1 (Thread #1608)",
    "sources": [
      "reddit"
    ],
    "subreddit": "worldnews",
    "why": "New post on r/worldnews \u2022 ~1m ago",
    "exampleUrl": "https://www.reddit.com/r/worldnews/comments/1rd4p5c/rworldnews_live_thread_russian_invasion_of/"
  },
  {
    "topic": "Senior Russian official claims Russian soldiers don't need visas to enter European countries",
    "sources": [
      "reddit"
    ],
    "subreddit": "worldnews",
    "why": "New post on r/worldnews \u2022 ~1m ago",
    "exampleUrl": "https://www.reddit.com/r/worldnews/comments/1rdcjb2/senior_russian_official_claims_russian_soldiers/"
  },
  {
    "topic": "Switzerland leads Europe in technology found in Russia's weapons",
    "sources": [
      "reddit"
    ],
    "subreddit": "worldnews",
    "why": "New post on r/worldnews \u2022 ~1m ago",
    "exampleUrl": "https://www.reddit.com/r/worldnews/comments/1rdhibo/switzerland_leads_europe_in_technology_found_in/"
  },
  {
    "topic": "U.S. has breached trade deal and Europe is ready to retaliate, top trade lawmaker tells CNBC",
    "sources": [
      "reddit"
    ],
    "subreddit": "worldnews",
    "why": "New post on r/worldnews \u2022 ~1m ago",
    "exampleUrl": "https://www.reddit.com/r/worldnews/comments/1rdffkk/us_has_breached_trade_deal_and_europe_is_ready_to/"
  },
  {
    "topic": "Making Friends Monday! Share your game tags here!",
    "sources": [
      "reddit"
    ],
    "subreddit": "gaming",
    "why": "New post on r/gaming \u2022 ~1m ago",
    "exampleUrl": "https://www.reddit.com/r/gaming/comments/1rcajz3/making_friends_monday_share_your_game_tags_here/"
  },
  {
    "topic": "Simple Questions Sunday!",
    "sources": [
      "reddit"
    ],
    "subreddit": "gaming",
    "why": "New post on r/gaming \u2022 ~1m ago",
    "exampleUrl": "https://www.reddit.com/r/gaming/comments/1pm7tip/simple_questions_sunday/"
  },
  {
    "topic": "Wolverine officially coming Sept 15",
    "sources": [
      "reddit"
    ],
    "subreddit": "gaming",
    "why": "New post on r/gaming \u2022 ~1m ago",
    "exampleUrl": "https://www.reddit.com/r/gaming/comments/1rdlw0s/wolverine_officially_coming_sept_15/"
  },
  {
    "topic": "$1 million in debt, devs on handheld Tony Hawk's Pro Skater saved the company by pitching \"fake\" screenshots that forced them to turn the GBA into a 3D gaming machine: \"Nobody could believe it\"",
    "sources": [
      "reddit"
    ],
    "subreddit": "gaming",
    "why": "New post on r/gaming \u2022 ~1m ago",
    "exampleUrl": "https://www.reddit.com/r/gaming/comments/1rdppqz/1_million_in_debt_devs_on_handheld_tony_hawks_pro/"
  },
  {
    "topic": "Death Stranding 2 PC specs",
    "sources": [
      "reddit"
    ],
    "subreddit": "gaming",
    "why": "New post on r/gaming \u2022 ~1m ago",
    "exampleUrl": "https://www.reddit.com/r/gaming/comments/1rdhra6/death_stranding_2_pc_specs/"
  },
  {
    "topic": "Aaya Sher - Lyrical | The Paradise | Nani | Anirudh Ravichander | Srikanth Odela",
    "sources": [
      "youtube"
    ],
    "why": "Trending on YouTube \u2022 4,781,247 views \u2022 ~374m old",
    "exampleUrl": "https://www.youtube.com/watch?v=iAtoZar5W58"
  },
  {
    "topic": "Major UPDATE Live Today in ARC Raiders?! - Embark Partner",
    "sources": [
      "youtube"
    ],
    "why": "Trending on YouTube \u2022 142,271 views \u2022 ~46m old",
    "exampleUrl": "https://www.youtube.com/watch?v=1zsbG1n6rZc"
  },
  {
    "topic": "The Madison | Official Trailer | Paramount+",
    "sources": [
      "youtube"
    ],
    "why": "Trending on YouTube \u2022 147,857 views \u2022 ~298m old",
    "exampleUrl": "https://www.youtube.com/watch?v=OSb-X_YkLg4"
  },
  {
    "topic": "Marvel's Wolverine - Release Date Reveal",
    "sources": [
      "youtube"
    ],
    "why": "Trending on YouTube \u2022 74,972 views \u2022 ~235m old",
    "exampleUrl": "https://www.youtube.com/watch?v=BMU9iACrRO8"
  },
  {
    "topic": "Honest Trailers | Predator: Badlands",
    "sources": [
      "youtube"
    ],
    "why": "Trending on YouTube \u2022 48,050 views \u2022 ~178m old",
    "exampleUrl": "https://www.youtube.com/watch?v=cflGcCLqBzk"
  },
  {
    "topic": "RE4 randomizer...CAN YOU CHILL OUT?! \ud83d\udd34Full Stream\ud83d\udd34 (2-23)",
    "sources": [
      "youtube"
    ],
    "why": "Trending on YouTube \u2022 138,531 views \u2022 ~580m old",
    "exampleUrl": "https://www.youtube.com/watch?v=ZtPZ6S0gaM4"
  },
  {
    "topic": "Marvel's Wolverine - Official Release Date Reveal Trailer",
    "sources": [
      "youtube"
    ],
    "why": "Trending on YouTube \u2022 50,755 views \u2022 ~222m old",
    "exampleUrl": "https://www.youtube.com/watch?v=0XdGFYXkk6w"
  },
  {
    "topic": "For All Mankind \u2014 Season 5 Official Trailer | Apple TV",
    "sources": [
      "youtube"
    ],
    "why": "Trending on YouTube \u2022 79,592 views \u2022 ~358m old",
    "exampleUrl": "https://www.youtube.com/watch?v=zojwKLlY_H8"
  },
  {
    "topic": "Slayyyter - OLD TECHNOLOGY (Official Video)",
    "sources": [
      "youtube"
    ],
    "why": "Trending on YouTube \u2022 25,986 views \u2022 ~238m old",
    "exampleUrl": "https://www.youtube.com/watch?v=rg1CEKM0nd0"
  }
]