[
  {
    "topic": "] REMINDER] ANY political content will earn an immediate 30-day ban\"",
    "sources": [
      "reddit"
    ],
    "subreddit": "funny",
    "why": "New post on r/funny \u2022 ~1m ago",
    "exampleUrl": "https://www.reddit.com/r/funny/comments/160kuuf/reminder_any_political_content_will_earn_an/"
  },
  {
    "topic": "3/10 Dismount \ud83d\ude05",
    "sources": [
      "reddit"
    ],
    "subreddit": "funny",
    "why": "New post on r/funny \u2022 ~1m ago",
    "exampleUrl": "https://www.reddit.com/r/funny/comments/1qif1q4/310_dismount/"
  },
  {
    "topic": "Pretending to be a car",
    "sources": [
      "reddit"
    ],
    "subreddit": "funny",
    "why": "New post on r/funny \u2022 ~1m ago",
    "exampleUrl": "https://www.reddit.com/r/funny/comments/1qimv1h/pretending_to_be_a_car/"
  },
  {
    "topic": "You steal it, you wear it.",
    "sources": [
      "reddit"
    ],
    "subreddit": "funny",
    "why": "New post on r/funny \u2022 ~1m ago",
    "exampleUrl": "https://www.reddit.com/r/funny/comments/1qi743l/you_steal_it_you_wear_it/"
  },
  {
    "topic": "Too broke for water \ud83d\ude2d",
    "sources": [
      "reddit"
    ],
    "subreddit": "funny",
    "why": "New post on r/funny \u2022 ~1m ago",
    "exampleUrl": "https://www.reddit.com/r/funny/comments/1qii6wo/too_broke_for_water/"
  },
  {
    "topic": "Why is this even allowed?",
    "sources": [
      "reddit"
    ],
    "subreddit": "youtube",
    "why": "New post on r/youtube \u2022 ~1m ago",
    "exampleUrl": "https://www.reddit.com/r/youtube/comments/1qhwe2j/why_is_this_even_allowed/"
  },
  {
    "topic": "Doritos are apparently a chocolate brand according to youtube",
    "sources": [
      "reddit"
    ],
    "subreddit": "youtube",
    "why": "New post on r/youtube \u2022 ~1m ago",
    "exampleUrl": "https://www.reddit.com/r/youtube/comments/1qij4ft/doritos_are_apparently_a_chocolate_brand/"
  },
  {
    "topic": "i\u2019m going to lose my mind with these ads.",
    "sources": [
      "reddit"
    ],
    "subreddit": "youtube",
    "why": "New post on r/youtube \u2022 ~1m ago",
    "exampleUrl": "https://www.reddit.com/r/youtube/comments/1qii8v9/im_going_to_lose_my_mind_with_these_ads/"
  },
  {
    "topic": "What Youtuber is this for you?",
    "sources": [
      "reddit"
    ],
    "subreddit": "youtube",
    "why": "New post on r/youtube \u2022 ~1m ago",
    "exampleUrl": "https://www.reddit.com/r/youtube/comments/1qi3yds/what_youtuber_is_this_for_you/"
  },
  {
    "topic": "Every year, every month.",
    "sources": [
      "reddit"
    ],
    "subreddit": "youtube",
    "why": "New post on r/youtube \u2022 ~1m ago",
    "exampleUrl": "https://www.reddit.com/r/youtube/comments/1qhxmns/every_year_every_month/"
  },
  {
    "topic": "Macron on Trump leaking their private messages: \"I stand by my words\"",
    "sources": [
      "reddit"
    ],
    "subreddit": "worldnews",
    "why": "New post on r/worldnews \u2022 ~1m ago",
    "exampleUrl": "https://www.reddit.com/r/worldnews/comments/1qifvu2/macron_on_trump_leaking_their_private_messages_i/"
  },
  {
    "topic": "/r/WorldNews Live Thread: Russian Invasion of Ukraine Day 1427, Part 1 (Thread #1574)",
    "sources": [
      "reddit"
    ],
    "subreddit": "worldnews",
    "why": "New post on r/worldnews \u2022 ~1m ago",
    "exampleUrl": "https://www.reddit.com/r/worldnews/comments/1qinlns/rworldnews_live_thread_russian_invasion_of/"
  },
  {
    "topic": "Trump doubles down on Greenland threats, saying there is 'no going back'",
    "sources": [
      "reddit"
    ],
    "subreddit": "worldnews",
    "why": "New post on r/worldnews \u2022 ~1m ago",
    "exampleUrl": "https://www.reddit.com/r/worldnews/comments/1qio5bh/trump_doubles_down_on_greenland_threats_saying/"
  },
  {
    "topic": "Trump says Iran would be wiped off Earth if something happens to him",
    "sources": [
      "reddit"
    ],
    "subreddit": "worldnews",
    "why": "New post on r/worldnews \u2022 ~1m ago",
    "exampleUrl": "https://www.reddit.com/r/worldnews/comments/1qijxsq/trump_says_iran_would_be_wiped_off_earth_if/"
  },
  {
    "topic": "Danish pension fund to sell $100 million in Treasuries, citing 'poor' U.S. government finances",
    "sources": [
      "reddit"
    ],
    "subreddit": "worldnews",
    "why": "New post on r/worldnews \u2022 ~1m ago",
    "exampleUrl": "https://www.reddit.com/r/worldnews/comments/1qi7tdk/danish_pension_fund_to_sell_100_million_in/"
  },
  {
    "topic": "Making Friends Monday! Share your game tags here!",
    "sources": [
      "reddit"
    ],
    "subreddit": "gaming",
    "why": "New post on r/gaming \u2022 ~1m ago",
    "exampleUrl": "https://www.reddit.com/r/gaming/comments/1qgx8q5/making_friends_monday_share_your_game_tags_here/"
  },
  {
    "topic": "I miss when PC games came in a big box",
    "sources": [
      "reddit"
    ],
    "subreddit": "gaming",
    "why": "New post on r/gaming \u2022 ~1m ago",
    "exampleUrl": "https://www.reddit.com/r/gaming/comments/1qile2s/i_miss_when_pc_games_came_in_a_big_box/"
  },
  {
    "topic": "Still 1 of my favorite classic examples between Japanese and American cover arts...",
    "sources": [
      "reddit"
    ],
    "subreddit": "gaming",
    "why": "New post on r/gaming \u2022 ~1m ago",
    "exampleUrl": "https://www.reddit.com/r/gaming/comments/1qi9oiv/still_1_of_my_favorite_classic_examples_between/"
  },
  {
    "topic": "Highguard Is One Week Away, And The Only Person Who's Advertised It Is Geoff Keighley",
    "sources": [
      "reddit"
    ],
    "subreddit": "gaming",
    "why": "New post on r/gaming \u2022 ~1m ago",
    "exampleUrl": "https://www.reddit.com/r/gaming/comments/1qi3kow/highguard_is_one_week_away_and_the_only_person/"
  },
  {
    "topic": "Show me the Champion of Light \ud83c\udfb6 (Alan Wake 2, 2023)",
    "sources": [
      "reddit"
    ],
    "subreddit": "gaming",
    "why": "New post on r/gaming \u2022 ~1m ago",
    "exampleUrl": "https://www.reddit.com/r/gaming/comments/1qie1gh/show_me_the_champion_of_light_alan_wake_2_2023/"
  },
  {
    "topic": "I Got the new TACO BASE in Steal A Brainrot..",
    "sources": [
      "youtube"
    ],
    "why": "Trending on YouTube \u2022 1,082,956 views \u2022 ~477m old",
    "exampleUrl": "https://www.youtube.com/watch?v=ciURKxo-zsU"
  },
  {
    "topic": "I Got Trained By the World's Best Minecraft Player",
    "sources": [
      "youtube"
    ],
    "why": "Trending on YouTube \u2022 964,575 views \u2022 ~554m old",
    "exampleUrl": "https://www.youtube.com/watch?v=D7hmj_cT-Qk"
  },
  {
    "topic": "We Played The Most Hilarious Game of 2026",
    "sources": [
      "youtube"
    ],
    "why": "Trending on YouTube \u2022 632,505 views \u2022 ~485m old",
    "exampleUrl": "https://www.youtube.com/watch?v=AUWH7uHPgOY"
  },
  {
    "topic": "OK, Let\u2019s Talk About the Avengers Doomsday TIMESTAMPS\u2026",
    "sources": [
      "youtube"
    ],
    "why": "Trending on YouTube \u2022 145,297 views \u2022 ~613m old",
    "exampleUrl": "https://www.youtube.com/watch?v=U4u0cdUgV5Q"
  },
  {
    "topic": "Luis Fonsi, Feid - CAMBIAR\u00c9 (Official Video)",
    "sources": [
      "youtube"
    ],
    "why": "Trending on YouTube \u2022 105,813 views \u2022 ~478m old",
    "exampleUrl": "https://www.youtube.com/watch?v=q-mWC7xuuEA"
  },
  {
    "topic": "Avengers Doomsday Trailer What Happened To Hulk & Spider-Man",
    "sources": [
      "youtube"
    ],
    "why": "Trending on YouTube \u2022 79,875 views \u2022 ~429m old",
    "exampleUrl": "https://www.youtube.com/watch?v=dDAb7PiixUc"
  },
  {
    "topic": "BAK Jay - Reap 2 (Official Music Video)",
    "sources": [
      "youtube"
    ],
    "why": "Trending on YouTube \u2022 27,054 views \u2022 ~478m old",
    "exampleUrl": "https://www.youtube.com/watch?v=Gk4tzP34ANY"
  },
  {
    "topic": "Topoppgen - twin towers (Official Video)",
    "sources": [
      "youtube"
    ],
    "why": "Trending on YouTube \u2022 32,718 views \u2022 ~717m old",
    "exampleUrl": "https://www.youtube.com/watch?v=v1E2jOkTtng"
  },
  {
    "topic": "FattMack - White Knight [Official Music Video]",
    "sources": [
      "youtube"
    ],
    "why": "Trending on YouTube \u2022 28,236 views \u2022 ~658m old",
    "exampleUrl": "https://www.youtube.com/watch?v=o0Q9D2Tn_NY"
  },
  {
    "topic": "Hunxho - Free Da Press [Official Video]",
    "sources": [
      "youtube"
    ],
    "why": "Trending on YouTube \u2022 27,263 views \u2022 ~688m old",
    "exampleUrl": "https://www.youtube.com/watch?v=l_FAD5ePJaM"
  }
]