[
  {
    "topic": "Must have been a tough morning.",
    "sources": [
      "reddit"
    ],
    "subreddit": "funny",
    "why": "New post on r/funny \u2022 ~1m ago",
    "exampleUrl": "https://www.reddit.com/r/funny/comments/1t3itmr/must_have_been_a_tough_morning/"
  },
  {
    "topic": "] REMINDER] ANY political content will earn an immediate 30-day ban\"",
    "sources": [
      "reddit"
    ],
    "subreddit": "funny",
    "why": "New post on r/funny \u2022 ~1m ago",
    "exampleUrl": "https://www.reddit.com/r/funny/comments/160kuuf/reminder_any_political_content_will_earn_an/"
  },
  {
    "topic": "Horizontal Meeting",
    "sources": [
      "reddit"
    ],
    "subreddit": "funny",
    "why": "New post on r/funny \u2022 ~1m ago",
    "exampleUrl": "https://www.reddit.com/r/funny/comments/1t3actx/horizontal_meeting/"
  },
  {
    "topic": "My Retired Dad Will Not Stop Making These Satirical Newsletters\u2026 What Do You Think of the May Edition?",
    "sources": [
      "reddit"
    ],
    "subreddit": "funny",
    "why": "New post on r/funny \u2022 ~1m ago",
    "exampleUrl": "https://www.reddit.com/r/funny/comments/1t3rif6/my_retired_dad_will_not_stop_making_these/"
  },
  {
    "topic": "Why on earth did he change multiple lanes?",
    "sources": [
      "reddit"
    ],
    "subreddit": "funny",
    "why": "New post on r/funny \u2022 ~1m ago",
    "exampleUrl": "https://www.reddit.com/r/funny/comments/1t3gz4y/why_on_earth_did_he_change_multiple_lanes/"
  },
  {
    "topic": "\"Boohoo I can't make money off of someone else's content boohoohoo\"",
    "sources": [
      "reddit"
    ],
    "subreddit": "youtube",
    "why": "New post on r/youtube \u2022 ~1m ago",
    "exampleUrl": "https://www.reddit.com/r/youtube/comments/1t3q84c/boohoo_i_cant_make_money_off_of_someone_elses/"
  },
  {
    "topic": "Guy takes advantage of women and gets caught",
    "sources": [
      "reddit"
    ],
    "subreddit": "youtube",
    "why": "New post on r/youtube \u2022 ~1m ago",
    "exampleUrl": "https://www.reddit.com/r/youtube/comments/1t3jjos/guy_takes_advantage_of_women_and_gets_caught/"
  },
  {
    "topic": "Yo \ud83d\ude2d they calling this poor man\u2019s video ai slop",
    "sources": [
      "reddit"
    ],
    "subreddit": "youtube",
    "why": "New post on r/youtube \u2022 ~1m ago",
    "exampleUrl": "https://www.reddit.com/r/youtube/comments/1t3hnm0/yo_they_calling_this_poor_mans_video_ai_slop/"
  },
  {
    "topic": "why is every thumbnail cropped?",
    "sources": [
      "reddit"
    ],
    "subreddit": "youtube",
    "why": "New post on r/youtube \u2022 ~1m ago",
    "exampleUrl": "https://www.reddit.com/r/youtube/comments/1t2k2g1/why_is_every_thumbnail_cropped/"
  },
  {
    "topic": "Is it only me or does everyone thinks that youtube is having a lot of ads that too unskippable all of a sudden?",
    "sources": [
      "reddit"
    ],
    "subreddit": "youtube",
    "why": "New post on r/youtube \u2022 ~1m ago",
    "exampleUrl": "https://www.reddit.com/r/youtube/comments/1t3min9/is_it_only_me_or_does_everyone_thinks_that/"
  },
  {
    "topic": "Volodymyr Zelenskyy warned that Ukrainian drones may target Russia\u2019s May 9 Victory Day parade in Moscow",
    "sources": [
      "reddit"
    ],
    "subreddit": "worldnews",
    "why": "New post on r/worldnews \u2022 ~1m ago",
    "exampleUrl": "https://www.reddit.com/r/worldnews/comments/1t3jfnm/volodymyr_zelenskyy_warned_that_ukrainian_drones/"
  },
  {
    "topic": "/r/WorldNews Live Thread: Russian Invasion of Ukraine Day 1530, Part 1 (Thread #1677)",
    "sources": [
      "reddit"
    ],
    "subreddit": "worldnews",
    "why": "New post on r/worldnews \u2022 ~1m ago",
    "exampleUrl": "https://www.reddit.com/r/worldnews/comments/1t36xhr/rworldnews_live_thread_russian_invasion_of/"
  },
  {
    "topic": "/r/WorldNews Discussion Thread: US and Israel launch attack on Iran; Iran retaliates (Thread #17)",
    "sources": [
      "reddit"
    ],
    "subreddit": "worldnews",
    "why": "New post on r/worldnews \u2022 ~1m ago",
    "exampleUrl": "https://www.reddit.com/r/worldnews/comments/1t1399d/rworldnews_discussion_thread_us_and_israel_launch/"
  },
  {
    "topic": "As economic despair mounts, Russian official admits the country has had enough of Putin's war on Ukraine. \"We can\u2019t even take one region\"",
    "sources": [
      "reddit"
    ],
    "subreddit": "worldnews",
    "why": "New post on r/worldnews \u2022 ~1m ago",
    "exampleUrl": "https://www.reddit.com/r/worldnews/comments/1t3kjl6/as_economic_despair_mounts_russian_official/"
  },
  {
    "topic": "Putin shelters in bunkers amid \u2018assassination\u2019 fears",
    "sources": [
      "reddit"
    ],
    "subreddit": "worldnews",
    "why": "New post on r/worldnews \u2022 ~1m ago",
    "exampleUrl": "https://www.reddit.com/r/worldnews/comments/1t3ekny/putin_shelters_in_bunkers_amid_assassination_fears/"
  },
  {
    "topic": "Making Friends Monday! Share your game tags here!",
    "sources": [
      "reddit"
    ],
    "subreddit": "gaming",
    "why": "New post on r/gaming \u2022 ~1m ago",
    "exampleUrl": "https://www.reddit.com/r/gaming/comments/1t394t3/making_friends_monday_share_your_game_tags_here/"
  },
  {
    "topic": "The Steam Controller sold out in 30 minutes, utterly breaking Steam in the process",
    "sources": [
      "reddit"
    ],
    "subreddit": "gaming",
    "why": "New post on r/gaming \u2022 ~1m ago",
    "exampleUrl": "https://www.reddit.com/r/gaming/comments/1t3pgns/the_steam_controller_sold_out_in_30_minutes/"
  },
  {
    "topic": "007 First Light\u2019s campaign will last roughly 20 hours long",
    "sources": [
      "reddit"
    ],
    "subreddit": "gaming",
    "why": "New post on r/gaming \u2022 ~1m ago",
    "exampleUrl": "https://www.reddit.com/r/gaming/comments/1t3oaaq/007_first_lights_campaign_will_last_roughly_20/"
  },
  {
    "topic": "PSA: check your the batteries in your old games consoles",
    "sources": [
      "reddit"
    ],
    "subreddit": "gaming",
    "why": "New post on r/gaming \u2022 ~1m ago",
    "exampleUrl": "https://www.reddit.com/r/gaming/comments/1t3jihn/psa_check_your_the_batteries_in_your_old_games/"
  },
  {
    "topic": "Why do modern games have no cheat codes anymore like they had in 90s/2000s?",
    "sources": [
      "reddit"
    ],
    "subreddit": "gaming",
    "why": "New post on r/gaming \u2022 ~1m ago",
    "exampleUrl": "https://www.reddit.com/r/gaming/comments/1t3kxf9/why_do_modern_games_have_no_cheat_codes_anymore/"
  },
  {
    "topic": "BABYMONSTER - '\ucda4 (CHOOM)' M/V",
    "sources": [
      "youtube"
    ],
    "why": "Trending on YouTube \u2022 9,420,433 views \u2022 ~629m old",
    "exampleUrl": "https://www.youtube.com/watch?v=x3eqqoZPV_E"
  },
  {
    "topic": "CORTIS (\ucf54\ub974\ud2f0\uc2a4) 'TNT' Official MV",
    "sources": [
      "youtube"
    ],
    "why": "Trending on YouTube \u2022 1,738,445 views \u2022 ~653m old",
    "exampleUrl": "https://www.youtube.com/watch?v=kRpaqR5sbf0"
  },
  {
    "topic": "Free Skin. Free Scenery. Free Chests. \ud83d\udc40 Yes, You Read That Right!",
    "sources": [
      "youtube"
    ],
    "why": "Trending on YouTube \u2022 1,405,309 views \u2022 ~704m old",
    "exampleUrl": "https://www.youtube.com/watch?v=ajjkX8CeUc0"
  },
  {
    "topic": "Blue Lips",
    "sources": [
      "youtube"
    ],
    "why": "Trending on YouTube \u2022 582,019 views \u2022 ~650m old",
    "exampleUrl": "https://www.youtube.com/watch?v=SCySL2FKuCc"
  },
  {
    "topic": "The Boys Season 5 Episode 6 Trailer",
    "sources": [
      "youtube"
    ],
    "why": "Trending on YouTube \u2022 48,520 views \u2022 ~193m old",
    "exampleUrl": "https://www.youtube.com/watch?v=OYdHSvHDkcI"
  },
  {
    "topic": "Montreal Canadiens at Tampa Bay Lightning",
    "sources": [
      "youtube"
    ],
    "why": "Trending on YouTube \u2022 0 views \u2022 ~647m old",
    "exampleUrl": "https://www.youtube.com/watch?v=OAkcoNRC9x8"
  },
  {
    "topic": "Texas Rangers at Detroit Tigers",
    "sources": [
      "youtube"
    ],
    "why": "Trending on YouTube \u2022 0 views \u2022 ~521m old",
    "exampleUrl": "https://www.youtube.com/watch?v=mKvXd46fHz4"
  },
  {
    "topic": "FOX and Friends",
    "sources": [
      "youtube"
    ],
    "why": "Trending on YouTube \u2022 0 views \u2022 ~107m old",
    "exampleUrl": "https://www.youtube.com/watch?v=JG4dCtYefLc"
  },
  {
    "topic": "Minnesota Wild at Colorado Avalanche",
    "sources": [
      "youtube"
    ],
    "why": "Trending on YouTube \u2022 0 views \u2022 ~395m old",
    "exampleUrl": "https://www.youtube.com/watch?v=xK27NZxnllM"
  },
  {
    "topic": "Tell All: Part 2",
    "sources": [
      "youtube"
    ],
    "why": "Trending on YouTube \u2022 0 views \u2022 ~592m old",
    "exampleUrl": "https://www.youtube.com/watch?v=uTzr1XHAbAU"
  },
  {
    "topic": "Unfinished Business",
    "sources": [
      "youtube"
    ],
    "why": "Trending on YouTube \u2022 0 views \u2022 ~713m old",
    "exampleUrl": "https://www.youtube.com/watch?v=pnF7gmntYaA"
  },
  {
    "topic": "Cadillac Championship, Final Round",
    "sources": [
      "youtube"
    ],
    "why": "Trending on YouTube \u2022 0 views \u2022 ~471m old",
    "exampleUrl": "https://www.youtube.com/watch?v=oXu1q_XGRWo"
  },
  {
    "topic": "Shift 2: Speed",
    "sources": [
      "youtube"
    ],
    "why": "Trending on YouTube \u2022 0 views \u2022 ~670m old",
    "exampleUrl": "https://www.youtube.com/watch?v=zGN_WTL6_UQ"
  },
  {
    "topic": "Avengers: Infinity War",
    "sources": [
      "youtube"
    ],
    "why": "Trending on YouTube \u2022 0 views \u2022 ~567m old",
    "exampleUrl": "https://www.youtube.com/watch?v=5G0rk3p4-Cw"
  }
]