[
  {
    "topic": "\"Ahhhhh\"",
    "sources": [
      "reddit"
    ],
    "subreddit": "funny",
    "why": "New post on r/funny \u2022 ~1m ago",
    "exampleUrl": "https://www.reddit.com/r/funny/comments/1s4lc49/ahhhhh/"
  },
  {
    "topic": "] REMINDER] ANY political content will earn an immediate 30-day ban\"",
    "sources": [
      "reddit"
    ],
    "subreddit": "funny",
    "why": "New post on r/funny \u2022 ~1m ago",
    "exampleUrl": "https://www.reddit.com/r/funny/comments/160kuuf/reminder_any_political_content_will_earn_an/"
  },
  {
    "topic": "Every time",
    "sources": [
      "reddit"
    ],
    "subreddit": "funny",
    "why": "New post on r/funny \u2022 ~1m ago",
    "exampleUrl": "https://www.reddit.com/r/funny/comments/1s4nflk/every_time/"
  },
  {
    "topic": "First Time at The Famous Wiener Circle",
    "sources": [
      "reddit"
    ],
    "subreddit": "funny",
    "why": "New post on r/funny \u2022 ~1m ago",
    "exampleUrl": "https://www.reddit.com/r/funny/comments/1s46ucs/first_time_at_the_famous_wiener_circle/"
  },
  {
    "topic": "Borat introducing his sister scene never gets less awkward",
    "sources": [
      "reddit"
    ],
    "subreddit": "funny",
    "why": "New post on r/funny \u2022 ~1m ago",
    "exampleUrl": "https://www.reddit.com/r/funny/comments/1s468um/borat_introducing_his_sister_scene_never_gets/"
  },
  {
    "topic": "I hate this type of clickbait",
    "sources": [
      "reddit"
    ],
    "subreddit": "youtube",
    "why": "New post on r/youtube \u2022 ~1m ago",
    "exampleUrl": "https://www.reddit.com/r/youtube/comments/1s4i8uc/i_hate_this_type_of_clickbait/"
  },
  {
    "topic": "Remember back then 720 was HD,",
    "sources": [
      "reddit"
    ],
    "subreddit": "youtube",
    "why": "New post on r/youtube \u2022 ~1m ago",
    "exampleUrl": "https://www.reddit.com/r/youtube/comments/1s4hxiq/remember_back_then_720_was_hd/"
  },
  {
    "topic": "I give up.",
    "sources": [
      "reddit"
    ],
    "subreddit": "youtube",
    "why": "New post on r/youtube \u2022 ~1m ago",
    "exampleUrl": "https://www.reddit.com/r/youtube/comments/1s44zw0/i_give_up/"
  },
  {
    "topic": "All the creators out there keep hustling!!",
    "sources": [
      "reddit"
    ],
    "subreddit": "youtube",
    "why": "New post on r/youtube \u2022 ~1m ago",
    "exampleUrl": "https://www.reddit.com/r/youtube/comments/1s4e3xd/all_the_creators_out_there_keep_hustling/"
  },
  {
    "topic": "App has started adding fake progress bars to videos",
    "sources": [
      "reddit"
    ],
    "subreddit": "youtube",
    "why": "New post on r/youtube \u2022 ~1m ago",
    "exampleUrl": "https://www.reddit.com/r/youtube/comments/1s4c2iq/app_has_started_adding_fake_progress_bars_to/"
  },
  {
    "topic": "Report: Pentagon considers sending 10,000 additional troops to Middle East",
    "sources": [
      "reddit"
    ],
    "subreddit": "worldnews",
    "why": "New post on r/worldnews \u2022 ~1m ago",
    "exampleUrl": "https://www.reddit.com/r/worldnews/comments/1s4pbdv/report_pentagon_considers_sending_10000/"
  },
  {
    "topic": "/r/WorldNews Live Thread: Russian Invasion of Ukraine Day 1491, Part 1 (Thread #1638)",
    "sources": [
      "reddit"
    ],
    "subreddit": "worldnews",
    "why": "New post on r/worldnews \u2022 ~1m ago",
    "exampleUrl": "https://www.reddit.com/r/worldnews/comments/1s3x6xt/rworldnews_live_thread_russian_invasion_of/"
  },
  {
    "topic": "/r/WorldNews Discussion Thread: US and Israel launch attack on Iran; Iran retaliates (Thread #11)",
    "sources": [
      "reddit"
    ],
    "subreddit": "worldnews",
    "why": "New post on r/worldnews \u2022 ~1m ago",
    "exampleUrl": "https://www.reddit.com/r/worldnews/comments/1s402bg/rworldnews_discussion_thread_us_and_israel_launch/"
  },
  {
    "topic": "Iran starts to formalize its chokehold on the Strait of Hormuz with a 'toll booth' regime",
    "sources": [
      "reddit"
    ],
    "subreddit": "worldnews",
    "why": "New post on r/worldnews \u2022 ~1m ago",
    "exampleUrl": "https://www.reddit.com/r/worldnews/comments/1s4mbaw/iran_starts_to_formalize_its_chokehold_on_the/"
  },
  {
    "topic": "Trump extends pause on attacking Iran energy facilities to April 6",
    "sources": [
      "reddit"
    ],
    "subreddit": "worldnews",
    "why": "New post on r/worldnews \u2022 ~1m ago",
    "exampleUrl": "https://www.reddit.com/r/worldnews/comments/1s4ip8u/trump_extends_pause_on_attacking_iran_energy/"
  },
  {
    "topic": "Making Friends Monday! Share your game tags here!",
    "sources": [
      "reddit"
    ],
    "subreddit": "gaming",
    "why": "New post on r/gaming \u2022 ~1m ago",
    "exampleUrl": "https://www.reddit.com/r/gaming/comments/1s18tvq/making_friends_monday_share_your_game_tags_here/"
  },
  {
    "topic": "Epic CEO Tim Sweeney says 'employers will see a stream of resumes of once-in-a-lifetime quality' after the company laid off more than 1,000 people",
    "sources": [
      "reddit"
    ],
    "subreddit": "gaming",
    "why": "New post on r/gaming \u2022 ~1m ago",
    "exampleUrl": "https://www.reddit.com/r/gaming/comments/1s4bgho/epic_ceo_tim_sweeney_says_employers_will_see_a/"
  },
  {
    "topic": "Major PS5 and PS5 Pro price increase rumored, as Sony faces memory shortage",
    "sources": [
      "reddit"
    ],
    "subreddit": "gaming",
    "why": "New post on r/gaming \u2022 ~1m ago",
    "exampleUrl": "https://www.reddit.com/r/gaming/comments/1s4od6e/major_ps5_and_ps5_pro_price_increase_rumored_as/"
  },
  {
    "topic": "Psychological horror game disguised as a military shooter",
    "sources": [
      "reddit"
    ],
    "subreddit": "gaming",
    "why": "New post on r/gaming \u2022 ~1m ago",
    "exampleUrl": "https://www.reddit.com/r/gaming/comments/1s4ap1j/psychological_horror_game_disguised_as_a_military/"
  },
  {
    "topic": "[Crime Scene Cleaner] Who needs that much coffee, honestly?",
    "sources": [
      "reddit"
    ],
    "subreddit": "gaming",
    "why": "New post on r/gaming \u2022 ~1m ago",
    "exampleUrl": "https://www.reddit.com/r/gaming/comments/1s4j6bo/crime_scene_cleaner_who_needs_that_much_coffee/"
  },
  {
    "topic": "BTS 'SWIM' Dance Practice",
    "sources": [
      "youtube"
    ],
    "why": "Trending on YouTube \u2022 1,905,765 views \u2022 ~657m old",
    "exampleUrl": "https://www.youtube.com/watch?v=uYcNZLJ3KmU"
  },
  {
    "topic": "The End of Oak Street | Official Teaser Trailer",
    "sources": [
      "youtube"
    ],
    "why": "Trending on YouTube \u2022 1,181,468 views \u2022 ~597m old",
    "exampleUrl": "https://www.youtube.com/watch?v=IoHWPAN6FPg"
  },
  {
    "topic": "We Found The Best New Basketball Game",
    "sources": [
      "youtube"
    ],
    "why": "Trending on YouTube \u2022 211,008 views \u2022 ~269m old",
    "exampleUrl": "https://www.youtube.com/watch?v=ZNFUsVBPck4"
  },
  {
    "topic": "Stranger Things: Tales From \u201885 | Official Trailer | Netflix",
    "sources": [
      "youtube"
    ],
    "why": "Trending on YouTube \u2022 461,798 views \u2022 ~657m old",
    "exampleUrl": "https://www.youtube.com/watch?v=kajCUhg36R0"
  },
  {
    "topic": "I Controlled Emma's Brainrots...",
    "sources": [
      "youtube"
    ],
    "why": "Trending on YouTube \u2022 276,939 views \u2022 ~657m old",
    "exampleUrl": "https://www.youtube.com/watch?v=dFc9_MoVDqQ"
  },
  {
    "topic": "Masicka - Boasty (Official Music Video)",
    "sources": [
      "youtube"
    ],
    "why": "Trending on YouTube \u2022 67,066 views \u2022 ~237m old",
    "exampleUrl": "https://www.youtube.com/watch?v=JGw1UAYjFEY"
  },
  {
    "topic": "HARRY POTTER HBO TRAILER BREAKDOWN! Easter Eggs & Details You Missed!",
    "sources": [
      "youtube"
    ],
    "why": "Trending on YouTube \u2022 53,610 views \u2022 ~335m old",
    "exampleUrl": "https://www.youtube.com/watch?v=DghE3Xwz_i8"
  },
  {
    "topic": "Paul McCartney \u2013 The Boys of Dungeon Lane (Official Album Trailer)",
    "sources": [
      "youtube"
    ],
    "why": "Trending on YouTube \u2022 104,750 views \u2022 ~662m old",
    "exampleUrl": "https://www.youtube.com/watch?v=zckLcAuyG20"
  },
  {
    "topic": "VonOff1700 - Turn Me Up (G.K.S.Y.W.T.M.U) ft. Polo G (Official Video)",
    "sources": [
      "youtube"
    ],
    "why": "Trending on YouTube \u2022 62,252 views \u2022 ~537m old",
    "exampleUrl": "https://www.youtube.com/watch?v=yflFa6undWk"
  },
  {
    "topic": "PRESIDENT - Mercy (Visualiser)",
    "sources": [
      "youtube"
    ],
    "why": "Trending on YouTube \u2022 62,788 views \u2022 ~597m old",
    "exampleUrl": "https://www.youtube.com/watch?v=NhD3HC1jUeA"
  },
  {
    "topic": "Outnumbered",
    "sources": [
      "youtube"
    ],
    "why": "Trending on YouTube \u2022 0 views \u2022 ~173m old",
    "exampleUrl": "https://www.youtube.com/watch?v=ON7pFo3H__M"
  },
  {
    "topic": "Morning Joe",
    "sources": [
      "youtube"
    ],
    "why": "Trending on YouTube \u2022 0 views \u2022 ~281m old",
    "exampleUrl": "https://www.youtube.com/watch?v=KcCXcbnnyrk"
  },
  {
    "topic": "CNN News Central",
    "sources": [
      "youtube"
    ],
    "why": "Trending on YouTube \u2022 0 views \u2022 ~125m old",
    "exampleUrl": "https://www.youtube.com/watch?v=oPet9266Q84"
  },
  {
    "topic": "Squawk Box",
    "sources": [
      "youtube"
    ],
    "why": "Trending on YouTube \u2022 0 views \u2022 ~288m old",
    "exampleUrl": "https://www.youtube.com/watch?v=VLZoChz6VDw"
  }
]